metatensor/__init__.py
metatensor/_c_api.py
metatensor/_c_lib.py
metatensor/block.py
metatensor/labels.py
metatensor/status.py
metatensor/tensor.py
metatensor/utils.py
metatensor/version.py
metatensor/bin/metatensor.dll
metatensor/data/__init__.py
metatensor/data/array.py
metatensor/data/extract.py
metatensor/include/metatensor.h
metatensor/include/metatensor.hpp
metatensor/include/metatensor/arrays.hpp
metatensor/include/metatensor/block.hpp
metatensor/include/metatensor/errors.hpp
metatensor/include/metatensor/io.hpp
metatensor/include/metatensor/io_fwd.hpp
metatensor/include/metatensor/labels.hpp
metatensor/include/metatensor/tensor.hpp
metatensor/include/metatensor/version.h
metatensor/io/__init__.py
metatensor/io/_block.py
metatensor/io/_labels.py
metatensor/io/_tensor.py
metatensor/io/_utils.py
metatensor/lib/metatensor.dll.lib
metatensor/lib/cmake/metatensor/metatensor-config-version.cmake
metatensor/lib/cmake/metatensor/metatensor-config.cmake
metatensor_core-0.1.19.dist-info/licenses/AUTHORS
metatensor_core-0.1.19.dist-info/licenses/LICENSE
metatensor_core-0.1.19.dist-info/METADATA
metatensor_core-0.1.19.dist-info/WHEEL
metatensor_core-0.1.19.dist-info/top_level.txt
metatensor_core-0.1.19.dist-info/RECORD
